node_architecture/Client.py
node_architecture/__init__.py
node_architecture/abc.py
node_architecture/Server/Receiver.py
node_architecture/Server/Server.py
node_architecture/Server/__init__.py
sa_node_architecture-1.0.0.dist-info/LICENSE
sa_node_architecture-1.0.0.dist-info/METADATA
sa_node_architecture-1.0.0.dist-info/WHEEL
sa_node_architecture-1.0.0.dist-info/top_level.txt
sa_node_architecture-1.0.0.dist-info/RECORD
